{
  "edition": "fa.noor",
  "surah": 101,
  "blocks": [
    "<h1>آيه</h1>\n<p>الْقَارِعَةُ مَا الْقَارِعَةُ وَمَآ أَدْرَاكَ مَا الْقَارِعَةُ يَوْمَ يَكُونُ النَّاسُ كَالْفَرَاشِ الْمَبْثُوثِ وَتَكُونُ الْجِبَالُ كَالعِهْنِ الْمَنفُوشِ فَأَمَّا مَن ثَقُلَتْ مَوَازِينُهُ فَهُوَ فِى عِيشَةٍ رَّاضِيَةٍ وَأَمَّا مَنْ خَفَّتْ مَوَازِينُهُ فَأُمُّهُ هَاوِيَةٌ وَمَآ أَدْرَاكَ مَاهِيَهْ نَارٌ حَامِيَةٌ</p>\n<h1>ترجمه</h1>\n<p>| حادثه كوبنده. آن حادثه كوبنده چیست؟ و تو چه دانى آن حادثه كوبنده چیست؟ روزى كه مردم مانند پروانه ها پراكنده باشند. و كوهها مانند پشمِ رنگارنگِ زده شده. پس هر كس كفّه هاى (عمل خیرش در) ترازویش سنگین باشد، پس او در زندگى رضایت بخشى است. ولى هر كس كفّه هاى (كار خیرش در) ترازویش سبك باشد، پس در آغوش آتش است. و تو چه دانى آن چیست؟ آتشى سوزان.</p>\n<h1>نکته ها</h1>\n<p>|  «قارعة» از «قرع» به معناى كوبیدن چیزى بر چیزى است. یكى از نام هاى قیامت، «قارعة» است، زیرا با صیحه ى كوبنده آغاز مى شود و عذاب آن كوبنده است. در روایات مى خوانیم: حضرت على علیه السلام و فرزندان معصومش، میزان و معیار سنجش اعمال انسان ها در قیامت هستند.(۱۲۵) شاید دلیل آنكه كلمه «موازین» به صورت جمع آمده، این باشد كه كارهاى گوناگون انسان با ابزارهاى گوناگون سنجیده مى شود و هر كار، میزان مخصوص به خود را دارد. «موازین» جمع «میزان» به معناى وسیله سنجش است و روشن است كه اعمال انسان، امرى مادى و داراى وزن و جرم نیست كه با ترازوهاى معمولى سنجیده شود، بلكه هر دسته از اعمال انسان، معیار سنجش مخصوص به خود دارد. مادر براى همه فرزندان، مأوى و پناهگاه است، اما در آنجا مادر و پناهگاه گروهى از انسان ها دوزخ است. «هاویة» از «هَوى » به معناى سقوط است و دوزخ، محلّ سقوط گروهى است. «حامیة» از «حَمى » به معناى شدّت حرارت است. كوه هاى رنگارنگ در اثر قطعه قطعه شدن و خورد و خاك شدن، مثل پشم زده رنگارنگ مى شوند. «كالعهن المنفوش» «منفوش» از «نفش» به معناى باز كردن و كشیدن پشم است تا آنجا كه اجزاى آن از هم بگسلد.(۱۲۶) سبك و سنگینى مخصوص مادیات نیست. لذا به سخنان بى محتوى مى گویند: سخن سبك. شاید مراد از «ثقلت موازینه» و «خفّت موازینه» ارزش و كیفیّت عمل باشد و شاید هم مراد، قلّت و كثرت آن باشد. حضرت على علیه السلام فرمودند: مراد از سبكى عمل، كم بودن عمل و مراد از سنگینى عمل، زیادى آن است. «قلّة الحساب و كثرته»(۱۲۷) شخصى سلمان را تحقیر كرد كه تو كیستى و چیستى؟ پاسخ داد: اول من و تو نطفه و آخر من و تو مردار است. این دنیاست، اما در قیامت، «مَن ثقلت موازینه فهو الكریم و من خفّت موازینه فهو لئیم»(۱۲۸) هر كس میزان او سنگین باشد، تكریم مى شود و هر كس سبك باشد، تحقیر و ملامت خواهد شد.</p>\n<hr />\n<p>۱۲۵) بحارالانوار، ج ۷، ص:۲۵۲. ۱۲۶) تفسیر راهنما. ۱۲۷) احتجاج طبرسى، ج ۱، ص ۳۶۳. به نقل راهنما. ۱۲۸) تفسیر نور الثقلین.</p>\n<h1>پيام ها</h1>\n<p>۱- قیامت، كوبنده مستكبران و روحیه هاى متكبّرانه است. «القارعة ما القارعة»</p>\n<p>۲- قیامت فراتر از فكر بشر است. حتى پیامبر بدون بیان الهى از آن خبر ندارد. «و ما ادراك ما القارعة»</p>\n<p>۳- قیامت روز تحیّر و سرگردانى بشر است. «كالفراش المبثوث»</p>\n<p>۴- بهشت را به بها دهند نه بهانه. «من ثقلت موازینه فهو فى عیشة راضیة»</p>\n<p>۵ - زندگىِ سراسر شاد، مخصوص قیامت است. زیرا در دنیا در كنار كامیابى ها، دغدغه بیمارى، سرقت، حسادت، از دست دادن و گذرا بودن هست. «عیشة راضیة»</p>\n<p>۶- رضایت از زندگى، از نشانه هاى جامعه بهشتى است. «فهو فى عیشة راضیة»</p>\n<p>۷- مبناى كیفر و پاداش، عمل است كه با ترازوى عدل سنجیده مى شود. «ثقلت موازینه... خفّت موازینه»</p>"
  ],
  "ayahs": [
    {
      "ayah": 1,
      "block": 0
    },
    {
      "ayah": 2,
      "block": 0
    },
    {
      "ayah": 3,
      "block": 0
    },
    {
      "ayah": 4,
      "block": 0
    },
    {
      "ayah": 5,
      "block": 0
    },
    {
      "ayah": 6,
      "block": 0
    },
    {
      "ayah": 7,
      "block": 0
    },
    {
      "ayah": 8,
      "block": 0
    },
    {
      "ayah": 9,
      "block": 0
    },
    {
      "ayah": 10,
      "block": 0
    },
    {
      "ayah": 11,
      "block": 0
    }
  ]
}