{
  "edition": "ar.burhan",
  "surah": 96,
  "blocks": [
    "<div class=\"tafsir-arabic\" lang=\"ar\" dir=\"rtl\"><p dir=\"rtl\" lang=\"ar\">قوله تعالى: { بِسمِ ٱللهِ ٱلرَّحْمٰنِ ٱلرَّحِيـمِ * ٱقْرَأْ بِٱسْمِ رَبِّكَ ٱلَّذِي خَلَقَ * خَلَقَ ٱلإِنسَانَ مِنْ عَلَقٍ } [العلق: 1-2] - إلى قوله تعالى - { كَلاَّ لاَ تُطِعْهُ وَٱسْجُدْ وَٱقْتَرِب } [العلق: 19].</p><p dir=\"rtl\" lang=\"ar\">- علي بن إبراهيم، قال: حدثنا أحمد بن محمد الشيباني، قال: حدثنا محمد بن أحمد، قال:</p><p dir=\"rtl\" lang=\"ar\">حدثنا إسحاق بن محمد، قال: حدثنا محمد بن علي، قال: حدثنا عثمان بن يوسف، عن عبد الله بن كيسان، عن أبي جعفر (عليه السلام)، قال:</p><p dir=\"rtl\" lang=\"ar\">قلت: تقدم باب في مقدمة الكتاب في أول ما نزل من القرآن.</p><p dir=\"rtl\" lang=\"ar\">- علي بن إبراهيم، في معنى السورة، قوله: { ٱقْرَأْ بِٱسْمِ رَبِّكَ } ، قال: اقرأ بسم الله الرحمن الرحيم { ٱلَّذِي خَلَقَ * خَلَقَ ٱلإِنسَانَ مِنْ عَلَقٍ } ، قال: من دم { ٱقْرَأْ وَرَبُّكَ ٱلأَكْرَمُ * ٱلَّذِى عَلَّمَ بِٱلْقَلَمِ } يعني علم الإنسان الكتابة التي تتم بها أمور الدنيا في مشارق الأرض و مغاربها.</p><p dir=\"rtl\" lang=\"ar\">ثم قال: { كَلاَّ إِنَّ ٱلإِنسَانَ لَيَطْغَىٰ * أَن رَّآهُ ٱسْتَغْنَىٰ } قال: إن الإنسان إذا استغنى يكفر و يطغى و ينكر { إِنَّ إِلَىٰ رَبِّكَ ٱلرُّجْعَىٰ }.</p><p dir=\"rtl\" lang=\"ar\">قوله: { أَرَأَيْتَ ٱلَّذِي يَنْهَىٰ * عَبْداً إِذَا صَلَّىٰ } ، قال: كان الوليد بن المغيرة ينهى الناس عن الصلاة، و أن يطاع الله و رسوله، فقال الله: { أَرَأَيْتَ ٱلَّذِي يَنْهَىٰ * عَبْداً إِذَا صَلَّىٰ }.</p><p dir=\"rtl\" lang=\"ar\">قول الله عز و جل: { أَرَأَيْتَ إِن كَذَّبَ وَتَوَلَّىٰ * أَلَمْ يَعْلَم بِأَنَّ ٱللَّهَ يَرَىٰ * كَلاَّ لَئِن لَّمْ يَنتَهِ لَنَسْفَعاً بِٱلنَّاصِيَةِ } أي لنأخذنه بالناصية، فنلقيه في النار.</p><p dir=\"rtl\" lang=\"ar\">قوله: { فَلْيَدْعُ نَادِيَهُ } قال: لما مات أبو طالب، نادى أبو جهل و الوليد عليهما لعائن الله: هلموا فاقتلوا محمدا، فقد مات الذي كان ينصره، فقال الله: { فَلْيَدْعُ نَادِيَهُ * سَنَدْعُ ٱلزَّبَانِيَةَ } ، قال: كما دعا إلى قتل رسول الله (صلى الله عليه و آله)، نحن أيضا ندعو الزبانية.</p><p dir=\"rtl\" lang=\"ar\">ثم قال: { كَلاَّ لاَ تُطِعْهُ وَٱسْجُدْ وَٱقْتَرِب } أي لا يطيعون لما دعاهم إليه، لأن رسول الله (صلى الله عليه و آله) أجاره مطعم بن عدي بن نوفل بن عبد مناف و لم يجسر عليه أحد.</p><p dir=\"rtl\" lang=\"ar\">- محمد بن يعقوب: عن علي بن محمد، عن سهل بن زياد، عن الوشاء، قال: سمعت الرضا (عليه السلام) يقول: \" أقرب ما يكون العبد من الله عز و جل و هو ساجد، و ذلك قوله عز و جل: { وَٱسْجُدْ وَٱقْتَرِب } \".</p><p dir=\"rtl\" lang=\"ar\">- و عنه: عن علي بن إبراهيم، عن هارون بن مسلم، عن مسعدة بن صدقة، عن أبي عبد الله (عليه السلام)، قال: \" قال رسول الله (صلى الله عليه و آله): ما خلق الله عز و جل خلقا إلا و قد أمر عليه [آخر] يغلبه فيه، و ذلك أن الله تبارك و تعالى لما خلق البحار السفلى فخرت و زخرت، و قالت: أي شيء يغلبني؟ فخلق الأرض فسطحها على ظهرها [فذلت]، ثم إن الأرض فخرت، و قالت: أي شيء يغلبني؟ فخلق الجبال و أثبتها على ظهرها أوتادا من أن تميد بما عليها، فذلت الأرض و استقرت، ثم إن الجبال فخرت على الأرض، فشمخت و استطالت، و قالت: أي شيء يغلبني؟ فخلق الله الحديد و قطعها، فقرت الجبال و ذلت، ثم إن الحديد فخر على الجبال، و قال:</p><p dir=\"rtl\" lang=\"ar\">أي شيء يغلبني؟ فخلق الله النار فأذابت الحديد [فذل الحديد]، ثم إن النار زفرت و شهقت [و فخرت] و قالت: أي شيء يغلبني؟ فخلق الماء فأطفأها فذلت، ثم إن الماء فخر و زخر، و قال: أي شيء يغلبني؟ فخلق الله الريح، فحركت أمواجه و أثارت ما في قعره و حبسته عن مجاريه، فذل الماء، ثم إن الريح فخرت و عصفت، و لوحت أذيالها، و قالت: أي شيء يغلبني؟ فخلق الله الإنسان، فبنى و احتال، و اتخذ ما يستر به عن الريح و غيرها، فذلت الريح، ثم إن الإنسان طغى و قال: من أشد مني قوة؟ فخلق الله له الموت فقهره [فذل الإنسان]، ثم إن الموت فخر في نفسه، و قال الله عز و جل: لا تفخر فإني ذابحك بين الفريقين: أهل الجنة، و أهل النار، ثم لا أحييك أبدا، فترجى أو تخاف \".</p><p dir=\"rtl\" lang=\"ar\">و قال أيضا: \" الحلم يغلب الغضب، و الرحمة تغلب السخط، و الصدقة تغلب الخطيئة \" ثم قال أبو عبد الله (عليه السلام): \" ما أشبه هذا مما [قد] يغلب غيره! \".</p></div>"
  ],
  "ayahs": [
    {
      "ayah": 1,
      "block": 0
    },
    {
      "ayah": 2,
      "block": 0
    },
    {
      "ayah": 3,
      "block": 0
    },
    {
      "ayah": 4,
      "block": 0
    },
    {
      "ayah": 5,
      "block": 0
    },
    {
      "ayah": 6,
      "block": 0
    },
    {
      "ayah": 7,
      "block": 0
    },
    {
      "ayah": 8,
      "block": 0
    },
    {
      "ayah": 9,
      "block": 0
    },
    {
      "ayah": 10,
      "block": 0
    },
    {
      "ayah": 11,
      "block": 0
    },
    {
      "ayah": 12,
      "block": 0
    },
    {
      "ayah": 13,
      "block": 0
    },
    {
      "ayah": 14,
      "block": 0
    },
    {
      "ayah": 15,
      "block": 0
    },
    {
      "ayah": 16,
      "block": 0
    },
    {
      "ayah": 17,
      "block": 0
    },
    {
      "ayah": 18,
      "block": 0
    },
    {
      "ayah": 19,
      "block": 0
    }
  ]
}