{
  "edition": "ar.mizan",
  "surah": 105,
  "blocks": [
    "<h2>( سورة الفيل مكية وهي خمس آيات )</h2>\n<hr />\n<div class=\"tafsir-arabic\" lang=\"ar\" dir=\"rtl\">أَلَمْ تَرَ كَيْفَ فَعَلَ رَبُّكَ بِأَصْحَـٰبِ ٱلْفِيلِ (١)</div>\n\n<div class=\"tafsir-arabic\" lang=\"ar\" dir=\"rtl\">أَلَمْ يَجْعَلْ كَيْدَهُمْ فِى تَضْلِيلٍ (٢)</div>\n\n<div class=\"tafsir-arabic\" lang=\"ar\" dir=\"rtl\">وَأَرْسَلَ عَلَيْهِمْ طَيْرًا أَبَابِيلَ (٣)</div>\n\n<div class=\"tafsir-arabic\" lang=\"ar\" dir=\"rtl\">تَرْمِيهِم بِحِجَارَةٍ مِّن سِجِّيلٍ (٤)</div>\n\n<div class=\"tafsir-arabic\" lang=\"ar\" dir=\"rtl\">فَجَعَلَهُمْ كَعَصْفٍ مَّأْكُولٍۭ (٥)</div>\n\n<h2>( بيان )</h2>\n<p>فيها إشارة إلى قصة أصحاب الفيل إذ قصدوا مكة لتخريب الكعبة المعظمة فأهلكهم الله بإرسال طير أبابيل ترميهم بحجارة من سجيل فجعلهم كعصف مأكول ، وهي من آيات الله الجلية التي لا سترة عليها ، وقد أرخوا بها وذكرها الجاهليون في أشعارهم ، والسورة مكية.</p>\n<p><strong>قوله تعالى :</strong> «<em>أَلَمْ تَرَ كَيْفَ فَعَلَ رَبُّكَ بِأَصْحابِ الْفِيلِ</em>» المراد بالرؤية العلم الظاهر ظهور الحس ، والاستفهام إنكاري ، والمعنى ألم تعلم كيف فعل ربك بأصحاب الفيل ، وقد كانت الواقعة عام ولد فيه النبي صلى‌الله‌عليه‌وآله.</p>\n<p><strong>قوله تعالى :</strong> «<em>أَلَمْ يَجْعَلْ كَيْدَهُمْ فِي تَضْلِيلٍ</em>» المراد بكيدهم سوء قصدهم بمكة وإرادتهم تخريب البيت الحرام ، والتضليل والإضلال واحد ، وجعل كيدهم في تضليل جعل سعيهم ضالا لا يهتدى إلى الغاية المقصودة منه فقد ساروا لتخريب الكعبة وانتهى بهم إلى هلاك أنفسهم.</p>\n<p><strong>قوله تعالى :</strong> «<em>وَأَرْسَلَ عَلَيْهِمْ طَيْراً أَبابِيلَ</em>» الأبابيل ـ كما قيل ـ جماعات في تفرقة زمرة زمرة ، والمعنى وأرسل الله على أصحاب الفيل جماعات متفرقة من الطير والآية والتي تتلوها عطف تفسير على قوله : «<em>أَلَمْ يَجْعَلْ كَيْدَهُمْ فِي تَضْلِيلٍ</em>».</p>\n<p><strong>قوله تعالى</strong>: «<em>تَرْمِيهِمْ بِحِجارَةٍ مِنْ سِجِّيلٍ</em>» أي ترمي أبابيل الطير أصحاب الفيل بحجارة من سجيل ، وقد تقدم معنى السجيل في تفسير قصص قوم لوط.</p>\n<p><strong>قوله تعالى :</strong> «<em>فَجَعَلَهُمْ كَعَصْفٍ مَأْكُولٍ</em>» العصف ورق الزرع والعصف المأكول ورق الزرع الذي أكل حبه أو قشر الحب الذي أكل لبه والمراد أنهم عادوا بعد وقوع السجيل عليهم أجسادا بلا أرواح أو أن الحجر بحرارته أحرق أجوافهم ، وقيل : المراد ورق الزرع الذي وقع فيها الأكال وهو أن يأكله الدود فيفسده وفسرت الآية ببعض وجوه أخر لا يناسب الأدب القرآني.</p>\n<h2>( بحث روائي )</h2>\n<p>في المجمع : أجمعت الرواة على أن ملك اليمن الذي قصد هدم الكعبة هو أبرهة بن الصباح الأشرم وقيل : إن كنيته أبو يكسوم ونقل عن الواقدي أنه جد النجاشي الذي كان على عهد رسول الله صلى‌الله‌عليه‌وآله.</p>\n<p>ثم ساق الكلام في قصة استيلائه على ملك اليمن إلى أن قال : ثم إنه بنى كعبة باليمن وجعل فيها قبابا من ذهب فأمر أهل مملكته بالحج إليها يضاهي بذلك البيت الحرام ، وإن رجلا من بني كنانة خرج حتى قدم اليمن فنظر إليها ثم قعد فيها يعني لحاجة الإنسان فدخلها أبرهة فوجد تلك العذرة فيها فقال : من اجترأ علي بهذا؟ ونصرانيتي لأهدمن ذلك البيت حتى لا يحجه حاج أبدا ودعا بالفيل وأذن قومه بالخروج ومن اتبعه من أهل اليمن ، وكان أكثر من اتبعه منهم عك والأشعرون وخثعم.</p>\n<p>قال : ثم خرج يسير حتى إذا كان ببعض طريقه بعث رجلا من بني سليم ليدعو الناس إلى حج بيته الذي بناه فتلقاه أيضا رجل من الحمس من بني كنانة فقتله فازداد بذلك حنقا وحث السير والانطلاق.</p>\n<p>وطلب من أهل الطائف دليلا فبعثوا معه رجلا من هذيل يقال له نفيل فخرج بهم يهديهم حتى إذا كانوا بالمغمس نزلوه وهو من مكة على ستة أميال فبعثوا مقدماتهم إلى</p>\n<p>مكة فخرجت قريش عباديد في رءوس الجبال وقالوا : لا طاقة لنا بقتال هؤلاء ولم يبق بمكة غير عبد المطلب بن هاشم أقام على سقايته وغير شيبة بن عثمان بن عبد الدار أقام على حجابة البيت فجعل عبد المطلب يأخذ بعضادتي الباب ثم يقول :</p>\n<p>لا هم أن المرء يمنع رحله فامنع جلالك</p>\n<p>لا يغلبوا بصليبهم ومحالهم عدوا محالك</p>\n<p>لا يدخلوا البلد الحرام إذا فأمر ما بدا لك</p>\n<p>ثم إن مقدمات أبرهة أصابت نعما لقريش فأصابت فيها مائتي بعير لعبد المطلب بن هاشم فلما بلغه ذلك خرج حتى أتى القوم ، وكان حاجب أبرهة رجلا من الأشعرين وكان له بعبد المطلب معرفة فاستأذن له على الملك وقال له : أيها الملك جاءك سيد قريش الذي يطعم إنسها في الحي ووحشها في الجبل فقال له : ائذن له.</p>\n<p>وكان عبد المطلب رجلا جسيما جميلا فلما رآه أبو يكسوم أعظمه أن يجلسه تحته وكره أن يجلسه معه على سريره فنزل من سريره فجلس على الأرض وأجلس عبد المطلب معه ثم قال : ما حاجتك؟ قال : حاجتي مائتا بعير لي أصابتها مقدمتك فقال أبو يكسوم : والله لقد رأيتك فأعجبتني ثم تكلمت فزهدت فيك فقال : ولم أيها الملك؟ قال : لأني جئت إلى بيت عزكم ومنعتكم من العرب وفضلكم في الناس وشرفكم عليهم ودينكم الذي تعبدون فجئت لأكسره وأصيبت لك مائتا بعير فسألتك عن حاجتك فكلمتني في إبلك ولم تطلب إلي في بيتكم.</p>\n<p>فقال له عبد المطلب : أيها الملك أنا أكلمك في مالي ولهذا البيت رب هو يمنعه لست أنا منه في شيء فراع ذلك أبو يكسوم وأمر برد إبل عبد المطلب عليه ثم رجع وأمست ليلتهم تلك الليلة كالحة نجومها كأنها تكلمهم كلاما لاقترابها منهم فأحست نفوسهم بالعذاب.</p>\n<p>إلى أن قال : حتى إذا كان مع طلوع الشمس طلعت عليهم الطير معها الحجارة فجعلت ترميهم ، وكل طائر في منقاره حجر وفي رجليه حجران وإذا رمت بذلك مضت وطلعت أخرى فلا يقع حجر من حجارتهم تلك على بطن إلا خرقه ولا عظم إلا أوهاه وثقبه ، وثاب أبو يكسوم راجعا قد أصابته بعض الحجارة فجعل كلما قدم أرضا انقطع له فيها إرب حتى إذا انتهى إلى اليمن لم يبق شيء إلا باده فلما قدمها تصدع صدره وانشق بطنه فهلك ولم يصب من الأشعرين وخثعم أحد ، الحديث.</p>\n<p><strong>أقول :</strong> وفي الروايات اختلاف شديد في خصوصيات القصة من أراد الوقوف عليها فعليه بمطولات السير والتواريخ.</p>\n<hr />"
  ],
  "ayahs": [
    {
      "ayah": 1,
      "block": 0
    },
    {
      "ayah": 2,
      "block": 0
    },
    {
      "ayah": 3,
      "block": 0
    },
    {
      "ayah": 4,
      "block": 0
    },
    {
      "ayah": 5,
      "block": 0
    }
  ]
}